realsense/__init__.py
realsense/wrapper.cpp
realsense/wrapper.cpython-310-darwin.so
realsense/wrapper.hpp
realsense/wrapper.pyx
realsense_applesilicon-0.1.6.dist-info/licenses/LICENSE
realsense_applesilicon-0.1.6.dist-info/METADATA
realsense_applesilicon-0.1.6.dist-info/WHEEL
realsense_applesilicon-0.1.6.dist-info/top_level.txt
realsense_applesilicon-0.1.6.dist-info/RECORD
