Metadata-Version: 2.4
Name: realsense-applesilicon
Version: 0.1.6
Summary: Python wrapper for Intel RealSense cameras on Apple Silicon
Author: James Ball
Author-email: James Ball <James@istarirobotics.com>
License-Expression: MIT
Classifier: Development Status :: 3 - Alpha
Classifier: Intended Audience :: Developers
Classifier: Operating System :: MacOS :: MacOS X
Classifier: Programming Language :: Python :: 3
Classifier: Programming Language :: Python :: 3.8
Classifier: Programming Language :: Python :: 3.9
Classifier: Programming Language :: Python :: 3.10
Classifier: Programming Language :: Python :: 3.11
Requires-Python: >=3.8
License-File: LICENSE
Requires-Dist: numpy<2.0.0,>=1.19.0
Requires-Dist: opencv-python<5.0.0,>=4.5.0
Requires-Dist: cython<1.0.0,>=0.29.0
Dynamic: author
Dynamic: license-file
Dynamic: requires-python
